{
  "config": "seed_3_unconstrained",
  "n_neurons": 38,
  "results": {
    "0.0": {
      "compliance_rate": 0.661,
      "n_compliant": 661,
      "n_total": 1000,
      "parse_failures": 0
    },
    "0.5": {
      "compliance_rate": 0.662,
      "n_compliant": 662,
      "n_total": 1000,
      "parse_failures": 0
    },
    "1.0": {
      "compliance_rate": 0.66,
      "n_compliant": 660,
      "n_total": 1000,
      "parse_failures": 0
    },
    "1.5": {
      "compliance_rate": 0.659,
      "n_compliant": 659,
      "n_total": 1000,
      "parse_failures": 0
    },
    "2.0": {
      "compliance_rate": 0.662,
      "n_compliant": 662,
      "n_total": 1000,
      "parse_failures": 0
    },
    "2.5": {
      "compliance_rate": 0.658,
      "n_compliant": 658,
      "n_total": 1000,
      "parse_failures": 0
    },
    "3.0": {
      "compliance_rate": 0.658,
      "n_compliant": 658,
      "n_total": 1000,
      "parse_failures": 0
    }
  }
}